LICENSE
MANIFEST.in
README.md
setup.cfg
setup.py
tp/__init__.py
tp/api.py
tp/version.py
tp.egg-info/PKG-INFO
tp.egg-info/SOURCES.txt
tp.egg-info/dependency_links.txt
tp.egg-info/not-zip-safe
tp.egg-info/top_level.txt