Metadata-Version: 1.1
Name: tp
Version: 0.2.0
Summary: TargetProcess API wrapper
Home-page: http://github.com/eduarbo/tp.py
Author: Eduardo Ruiz
Author-email: eduarbo@gmail.com
License: Apache 2.0
Keywords: targetprocess rest api wrapper
Platform: UNKNOWN
Classifier: Development Status :: 3 - Alpha
Classifier: License :: OSI Approved :: Apache Software License
Classifier: Programming Language :: Python :: 2.7
Classifier: Topic :: Utilities
